{"cameraMode":{"drawMode":0,"name":"Shaded","section":"Shading Mode"},"sceneLighting":true,"audioPlay":false,"sceneViewState":{"showFog":true,"showMaterialUpdate":false,"showSkybox":true,"showFlares":true,"showImageEffects":true,"showParticleSystems":true},"in2DMode":false,"pivot":{"x":20.476280212402345,"y":1.5445826053619385,"z":14.521015167236329},"rotation":{"x":-0.0006155560840852559,"y":-0.9979934096336365,"z":0.009877322241663933,"w":-0.06297382712364197},"size":4.189914703369141,"orthographic":false}